Metadata-Version: 2.1
Name: softspot
Version: 1.0.0
Summary: softspot
Home-page: https://gitlab.com/davricha/softspot
Author: David Richard, Geert Kapteijns
Author-email: ghkapteijns@gmail.com
License: UNKNOWN
Platform: UNKNOWN
Classifier: Programming Language :: Python :: 3
Classifier: License :: OSI Approved :: MIT License
Requires-Python: >=3.6
